Workbook

Sheet Compte de Résultat
A1: Compte de Résultat (k€)
C2: 2022A | D2: 2023A | E2: 2024A | F2: 2025E | G2: 2026E | H2: 2027E
A3: CHIFFRE D'AFFAIRES
A4: CA Produits | C4: 12400 | D4: 14200 | E4: 16800 | F4: 19000 | G4: 21500 | H4: 24000
A5: CA Services | C5: 3100 | D5: 3800 | E5: 4600 | F5: 5200 | G5: 5900 | H5: 6700
A6: Autres produits | C6: 500 | D6: 620 | E6: 740 | F6: 820 | G6: 900 | H6: 990
A7: Chiffre d'Affaires Total | C7: =SUM(C4:C6) -> 16000 | D7: =SUM(D4:D6) -> 18620 | E7: =SUM(E4:E6) -> 22140 | F7: =SUM(F4:F6) -> 25020 | G7: =SUM(G4:G6) -> 28300 | H7: =SUM(H4:H6) -> 31690
A8: Croissance YoY | C8: - | D8: =(D7-C7)/C7 -> 0.16375 | E8: =(E7-D7)/D7 -> 0.18904404 | F8: =(F7-E7)/E7 -> 0.1300813 | G8: =(G7-F7)/F7 -> 0.13109512 | H8: =(H7-G7)/G7 -> 0.11978799
A10: COÛT DES VENTES
A11: Achats consommés | C11: 7440 | D11: 8378 | E11: 9744 | F11: 10830 | G11: 11825 | H11: 12960
A12: Charges directes services | C12: 1240 | D12: 1520 | E12: 1840 | F12: 2080 | G12: 2360 | H12: 2680
A13: Total Coût des Ventes | C13: =SUM(C11:C12) -> 8680 | D13: =SUM(D11:D12) -> 9898 | E13: =SUM(E11:E12) -> 11584 | F13: =SUM(F11:F12) -> 12910 | G13: =SUM(G11:G12) -> 14185 | H13: =SUM(H11:H12) -> 15640
A14: % du CA | C14: =C13/C7 -> 0.5425 | D14: =D13/D7 -> 0.53157895 | E14: =E13/E7 -> 0.5232159 | F14: =F13/F7 -> 0.51598721 | G14: =G13/G7 -> 0.50123675 | H14: =H13/H7 -> 0.49353108
A16: MARGE BRUTE | C16: =C7-C13 -> 7320 | D16: =D7-D13 -> 8722 | E16: =E7-E13 -> 10556 | F16: =F7-F13 -> 12110 | G16: =G7-G13 -> 14115 | H16: =H7-H13 -> 16050
A17: Taux de Marge Brute | C17: =C16/C7 -> 0.4575 | D17: =D16/D7 -> 0.46842105 | E17: =E16/E7 -> 0.4767841 | F17: =F16/F7 -> 0.48401279 | G17: =G16/G7 -> 0.49876325 | H17: =H16/H7 -> 0.50646892
A19: CHARGES D'EXPLOITATION
A20: Frais commerciaux & marketing | C20: 1860 | D20: 2130 | E20: 2520 | F20: 2850 | G20: 3225 | H20: 3600
A21: Frais généraux & administratifs | C21: 740 | D21: 852 | E21: 1008 | F21: 1140 | G21: 1290 | H21: 1440
A22: Recherche & développement | C22: 620 | D22: 710 | E22: 840 | F22: 950 | G22: 1075 | H22: 1200
A23: Dotations aux amortissements | C23: 480 | D23: 550 | E23: 640 | F23: 700 | G23: 780 | H23: 860
A24: Total Charges d'Exploitation | C24: =SUM(C20:C23) -> 3700 | D24: =SUM(D20:D23) -> 4242 | E24: =SUM(E20:E23) -> 5008 | F24: =SUM(F20:F23) -> 5640 | G24: =SUM(G20:G23) -> 6370 | H24: =SUM(H20:H23) -> 7100
A25: % du CA | C25: =C24/C7 -> 0.23125 | D25: =D24/D7 -> 0.22781955 | E25: =E24/E7 -> 0.22619693 | F25: =F24/F7 -> 0.22541966 | G25: =G24/G7 -> 0.22508834 | H25: =H24/H7 -> 0.22404544
A27: EBITDA | C27: =C16-(C20+C21+C22) -> 4100 | D27: =D16-(D20+D21+D22) -> 5030 | E27: =E16-(E20+E21+E22) -> 6188 | F27: =F16-(F20+F21+F22) -> 7170 | G27: =G16-(G20+G21+G22) -> 8525 | H27: =H16-(H20+H21+H22) -> 9810
A28: Marge EBITDA | C28: =C27/C7 -> 0.25625 | D28: =D27/D7 -> 0.27013963 | E28: =E27/E7 -> 0.27949413 | F28: =F27/F7 -> 0.28657074 | G28: =G27/G7 -> 0.30123675 | H28: =H27/H7 -> 0.30956138
A30: RÉSULTAT D'EXPLOITATION (EBIT) | C30: =C27-C23 -> 3620 | D30: =D27-D23 -> 4480 | E30: =E27-E23 -> 5548 | F30: =F27-F23 -> 6470 | G30: =G27-G23 -> 7745 | H30: =H27-H23 -> 8950
A31: Marge opérationnelle | C31: =C30/C7 -> 0.22625 | D31: =D30/D7 -> 0.2406015 | E31: =E30/E7 -> 0.25058717 | F31: =F30/F7 -> 0.25859313 | G31: =G30/G7 -> 0.27367491 | H31: =H30/H7 -> 0.28242348
A33: RÉSULTAT FINANCIER
A34: Produits financiers | C34: 120 | D34: 145 | E34: 160 | F34: 175 | G34: 190 | H34: 210
A35: Charges financières | C35: -280 | D35: -310 | E35: -330 | F35: -350 | G35: -380 | H35: -420
A36: Autres éléments financiers | C36: 0 | D36: 0 | E36: 50 | F36: 0 | G36: 0 | H36: 0
A37: Résultat Financier Net | C37: =SUM(C34:C36) -> -160 | D37: =SUM(D34:D36) -> -165 | E37: =SUM(E34:E36) -> -120 | F37: =SUM(F34:F36) -> -175 | G37: =SUM(G34:G36) -> -190 | H37: =SUM(H34:H36) -> -210
A39: RÉSULTAT AVANT IMPÔT (EBT) | C39: =C30+C37 -> 3460 | D39: =D30+D37 -> 4315 | E39: =E30+E37 -> 5428 | F39: =F30+F37 -> 6295 | G39: =G30+G37 -> 7555 | H39: =H30+H37 -> 8740
A40: IMPÔTS SUR LES BÉNÉFICES
A41: Taux effectif d'imposition | C41: 0.25 | D41: 0.25 | E41: 0.25 | F41: 0.25 | G41: 0.25 | H41: 0.25
A42: Impôt sur les sociétés | C42: =-C39*C41 -> -865 | D42: =-D39*D41 -> -1078.75 | E42: =-E39*E41 -> -1357 | F42: =-F39*F41 -> -1573.75 | G42: =-G39*G41 -> -1888.75 | H42: =-H39*H41 -> -2185
A44: RÉSULTAT NET | C44: =C39+C42 -> 2595 | D44: =D39+D42 -> 3236.25 | E44: =E39+E42 -> 4071 | F44: =F39+F42 -> 4721.25 | G44: =G39+G42 -> 5666.25 | H44: =H39+H42 -> 6555
A45: Marge nette | C45: =C44/C7 -> 0.1621875 | D45: =D44/D7 -> 0.17380505 | E45: =E44/E7 -> 0.18387534 | F45: =F44/F7 -> 0.18869904 | G45: =G44/G7 -> 0.20022085 | H45: =H44/H7 -> 0.20684759
A47: MÉMO
A48: Effectif (ETP) | C48: 85 | D48: 98 | E48: 112 | F48: 125 | G48: 140 | H48: 155
A49: CA par ETP (k€) | C49: =C7/C48 -> 188.23529 | D49: =D7/D48 -> 190 | E49: =E7/E48 -> 197.67857 | F49: =F7/F48 -> 200.16 | G49: =G7/G48 -> 202.14286 | H49: =H7/H48 -> 204.45161

Sheet Bilan
A1: Bilan (k€)
C2: 2022A | D2: 2023A | E2: 2024A | F2: 2025E | G2: 2026E | H2: 2027E
A3: ACTIF IMMOBILISÉ
A4: Immobilisations incorporelles (net) | C4: 1200 | D4: 1150 | E4: 1080 | F4: 1010 | G4: 940 | H4: 880
A5: Immobilisations corporelles (net) | C5: 3800 | D5: 3650 | E5: 3900 | F5: 4200 | G5: 4600 | H5: 5000
A6: Immobilisations financières | C6: 400 | D6: 420 | E6: 450 | F6: 480 | G6: 510 | H6: 540
A7: Total Actif Immobilisé | C7: =SUM(C4:C6) -> 5400 | D7: =SUM(D4:D6) -> 5220 | E7: =SUM(E4:E6) -> 5430 | F7: =SUM(F4:F6) -> 5690 | G7: =SUM(G4:G6) -> 6050 | H7: =SUM(H4:H6) -> 6420
A9: ACTIF CIRCULANT
A10: Stocks | C10: 1800 | D10: 2100 | E10: 2450 | F10: 2720 | G10: 3060 | H10: 3400
A11: Créances clients | C11: 2600 | D11: 2980 | E11: 3520 | F11: 3980 | G11: 4500 | H11: 5040
A12: Autres créances & charges constatées | C12: 320 | D12: 380 | E12: 450 | F12: 510 | G12: 580 | H12: 650
A13: Trésorerie & équivalents | C13: 1850 | D13: 2200 | E13: 2650 | F13: 3100 | G13: 3650 | H13: 4280
A14: Total Actif Circulant | C14: =SUM(C10:C13) -> 6570 | D14: =SUM(D10:D13) -> 7660 | E14: =SUM(E10:E13) -> 9070 | F14: =SUM(F10:F13) -> 10310 | G14: =SUM(G10:G13) -> 11790 | H14: =SUM(H10:H13) -> 13370
A16: TOTAL ACTIF | C16: =C7+C14 -> 11970 | D16: =D7+D14 -> 12880 | E16: =E7+E14 -> 14500 | F16: =F7+F14 -> 16000 | G16: =G7+G14 -> 17840 | H16: =H7+H14 -> 19790
A18: CAPITAUX PROPRES
A19: Capital social | C19: 2000 | D19: 2000 | E19: 2000 | F19: 2000 | G19: 2000 | H19: 2000
A20: Réserves et report à nouveau | C20: 1800 | D20: 2300 | E20: 2900 | F20: 3550 | G20: 4290 | H20: 5100
A21: Résultat de l'exercice | C21: ='Compte de Résultat'!C44 -> 2595 | D21: ='Compte de Résultat'!D44 -> 3236.25 | E21: ='Compte de Résultat'!E44 -> 4071 | F21: ='Compte de Résultat'!F44 -> 4721.25 | G21: ='Compte de Résultat'!G44 -> 5666.25 | H21: ='Compte de Résultat'!H44 -> 6555
A22: Total Capitaux Propres | C22: =SUM(C19:C21) -> 6395 | D22: =SUM(D19:D21) -> 7536.25 | E22: =SUM(E19:E21) -> 8971 | F22: =SUM(F19:F21) -> 10271.25 | G22: =SUM(G19:G21) -> 11956.25 | H22: =SUM(H19:H21) -> 13655
A24: DETTES FINANCIÈRES
A25: Emprunts & dettes auprès des établissements de crédit | C25: 2500 | D25: 2300 | E25: 2800 | F25: 3100 | G25: 3400 | H25: 3700
A26: Dettes financières à long terme | C26: 1200 | D26: 1050 | E26: 900 | F26: 750 | G26: 600 | H26: 450
A27: Total Dettes Financières | C27: =SUM(C25:C26) -> 3700 | D27: =SUM(D25:D26) -> 3350 | E27: =SUM(E25:E26) -> 3700 | F27: =SUM(F25:F26) -> 3850 | G27: =SUM(G25:G26) -> 4000 | H27: =SUM(H25:H26) -> 4150
A29: DETTES D'EXPLOITATION
A30: Dettes fournisseurs | C30: 1850 | D30: 2050 | E30: 2400 | F30: 2700 | G30: 3050 | H30: 3400
A31: Dettes fiscales & sociales | C31: 620 | D31: 710 | E31: 840 | F31: 950 | G31: 1075 | H31: 1200
A32: Autres dettes & produits constatés | C32: 400 | D32: 450 | E32: 510 | F32: 580 | G32: 655 | H32: 730
A33: Total Dettes d'Exploitation | C33: =SUM(C30:C32) -> 2870 | D33: =SUM(D30:D32) -> 3210 | E33: =SUM(E30:E32) -> 3750 | F33: =SUM(F30:F32) -> 4230 | G33: =SUM(G30:G32) -> 4780 | H33: =SUM(H30:H32) -> 5330
A35: TOTAL PASSIF | C35: =C22+C27+C33 -> 12965 | D35: =D22+D27+D33 -> 14096.25 | E35: =E22+E27+E33 -> 16421 | F35: =F22+F27+F33 -> 18351.25 | G35: =G22+G27+G33 -> 20736.25 | H35: =H22+H27+H33 -> 23135
A37: VÉRIFICATION
A38: Actif − Passif (doit être = 0) | C38: =C16-C35 -> -995 | D38: =D16-D35 -> -1216.25 | E38: =E16-E35 -> -1921 | F38: =F16-F35 -> -2351.25 | G38: =G16-G35 -> -2896.25 | H38: =H16-H35 -> -3345
A40: RATIOS CLÉS
A41: Dette nette | C41: =C25+C26-C13 -> 1850 | D41: =D25+D26-D13 -> 1150 | E41: =E25+E26-E13 -> 1050 | F41: =F25+F26-F13 -> 750 | G41: =G25+G26-G13 -> 350 | H41: =H25+H26-H13 -> -130
A42: Gearing (Dette nette / CP) | C42: =C41/C22 -> 0.28928851 | D42: =D41/D22 -> 0.15259579 | E42: =E41/E22 -> 0.11704381 | F42: =F41/F22 -> 0.07301935 | G42: =G41/G22 -> 0.029273393 | H42: =H41/H22 -> -0.0095203222
A43: BFR (Stocks + Clients − Fournisseurs) | C43: =C10+C11-C30 -> 2550 | D43: =D10+D11-D30 -> 3030 | E43: =E10+E11-E30 -> 3570 | F43: =F10+F11-F30 -> 4000 | G43: =G10+G11-G30 -> 4510 | H43: =H10+H11-H30 -> 5040
A44: Ratio de liquidité générale (AC / DE) | C44: =C14/C33 -> 2.2891986 | D44: =D14/D33 -> 2.3862928 | E44: =E14/E33 -> 2.4186667 | F44: =F14/F33 -> 2.4373522 | G44: =G14/G33 -> 2.4665272 | H44: =H14/H33 -> 2.5084428
A45: Autonomie financière (CP / TA) | C45: =C22/C16 -> 0.5342523 | D45: =D22/D16 -> 0.58511258 | E45: =E22/E16 -> 0.61868966 | F45: =F22/F16 -> 0.64195313 | G45: =G22/G16 -> 0.67019339 | H45: =H22/H16 -> 0.68999495
